ucla_geotech_tools_ipyconsol-1.0.6-py3.7-nspkg.pth
ucla_geotech_tools/ipyconsol.cp37-win_amd64.pyd
ucla_geotech_tools/ipyconsol.ipynb
ucla_geotech_tools/.ipynb_checkpoints/ipyconsol-Copy1-checkpoint.ipynb
ucla_geotech_tools/.ipynb_checkpoints/ipyconsol-checkpoint.ipynb
ucla_geotech_tools_ipyconsol-1.0.6.dist-info/METADATA
ucla_geotech_tools_ipyconsol-1.0.6.dist-info/WHEEL
ucla_geotech_tools_ipyconsol-1.0.6.dist-info/namespace_packages.txt
ucla_geotech_tools_ipyconsol-1.0.6.dist-info/top_level.txt
ucla_geotech_tools_ipyconsol-1.0.6.dist-info/RECORD
